pyedurov2/__init__.py
pyedurov2/__main__.py
pyedurov2/utility.py
pyedurov2/hardware/__init__.py
pyedurov2/hardware/arduino.py
pyedurov2/hardware/camera.py
pyedurov2/hardware/system.py
pyedurov2/hardware/mock/__init__.py
pyedurov2/hardware/mock/arduino.py
pyedurov2/hardware/mock/camera.py
pyedurov2/hardware/mock/system.py
pyedurov2/server/__init__.py
pyedurov2/server/advertising.py
pyedurov2/server/cameraserver.py
pyedurov2/server/ioserver.py
pyedurov2/system/__init__.py
pyedurov2/system/pyedurov2.service
pyedurov2-0.3.0.dist-info/LICENSE
pyedurov2-0.3.0.dist-info/METADATA
pyedurov2-0.3.0.dist-info/WHEEL
pyedurov2-0.3.0.dist-info/entry_points.txt
pyedurov2-0.3.0.dist-info/top_level.txt
pyedurov2-0.3.0.dist-info/RECORD
