Metadata-Version: 2.1
Name: pyedurov2
Version: 0.3.0
Summary: Server package for Edu-ROV hardware v0.7
Home-page: https://github.com/simtind/edu-rover2-server
Author: Simen August Tinderholt
Author-email: simtind@gmail.com
License: UNKNOWN
Project-URL: Source, https://github.com/simtind/edu-rover2-server
Project-URL: Tracker, https://github.com/simtind/edu-rover2-server/issues
Keywords: ROV education
Platform: UNKNOWN
Classifier: Development Status :: 5 - Production/Stable
Classifier: License :: OSI Approved :: GNU General Public License v3 (GPLv3)
Classifier: Programming Language :: Python :: 3.7
Requires-Python: >=3.7
License-File: LICENSE
Requires-Dist: picamera
Requires-Dist: sense-hat
Requires-Dist: pyserial-asyncio
Requires-Dist: asyncio
Requires-Dist: psutil
Requires-Dist: websockets
Requires-Dist: aiortc
Requires-Dist: aiohttp
